langchain_glm/__init__.py
langchain_glm/agent_toolkits/__init__.py
langchain_glm/agent_toolkits/all_tools/__init__.py
langchain_glm/agent_toolkits/all_tools/code_interpreter_tool.py
langchain_glm/agent_toolkits/all_tools/drawing_tool.py
langchain_glm/agent_toolkits/all_tools/registry.py
langchain_glm/agent_toolkits/all_tools/struct_type.py
langchain_glm/agent_toolkits/all_tools/tool.py
langchain_glm/agent_toolkits/all_tools/web_browser_tool.py
langchain_glm/agents/__init__.py
langchain_glm/agents/all_tools_agent.py
langchain_glm/agents/all_tools_bind/base.py
langchain_glm/agents/format_scratchpad/all_tools.py
langchain_glm/agents/output_parsers/__init__.py
langchain_glm/agents/output_parsers/_utils.py
langchain_glm/agents/output_parsers/base.py
langchain_glm/agents/output_parsers/code_interpreter.py
langchain_glm/agents/output_parsers/drawing_tool.py
langchain_glm/agents/output_parsers/function.py
langchain_glm/agents/output_parsers/tools.py
langchain_glm/agents/output_parsers/web_browser.py
langchain_glm/agents/output_parsers/zhipuai_all_tools.py
langchain_glm/agents/zhipuai_all_tools/__init__.py
langchain_glm/agents/zhipuai_all_tools/base.py
langchain_glm/agents/zhipuai_all_tools/schema.py
langchain_glm/callbacks/__init__.py
langchain_glm/callbacks/agent_callback_handler.py
langchain_glm/chat_models/__init__.py
langchain_glm/chat_models/all_tools_message.py
langchain_glm/chat_models/base.py
langchain_glm/embeddings/__init__.py
langchain_glm/embeddings/base.py
langchain_glm/utils/__init__.py
langchain_glm/utils/history.py
langchain_glm-0.0.2.dist-info/LICENSE
langchain_glm-0.0.2.dist-info/METADATA
langchain_glm-0.0.2.dist-info/WHEEL
langchain_glm-0.0.2.dist-info/entry_points.txt
langchain_glm-0.0.2.dist-info/RECORD
