Metadata-Version: 2.1
Name: langchain-glm
Version: 0.0.2
Summary: 
License: MIT
Author: glide-the
Author-email: z2533736852@gamil.com
Requires-Python: >=3.8, !=2.7.*, !=3.0.*, !=3.1.*, !=3.2.*, !=3.3.*, !=3.4.*, !=3.5.*, !=3.6.*, !=3.7.*, !=3.12.*
Classifier: License :: OSI Approved :: MIT License
Classifier: Programming Language :: Python :: 3
Classifier: Programming Language :: Python :: 3.9
Classifier: Programming Language :: Python :: 3.10
Classifier: Programming Language :: Python :: 3.11
Requires-Dist: langchain (>=0.2.2,<0.3) ; python_full_version >= "3.8.1" and python_full_version != "3.9.7" and python_version < "3.12"
Requires-Dist: langchain-community (>=0.2.0,<0.3) ; python_full_version >= "3.8.1" and python_full_version != "3.9.7" and python_version < "4.0"
Requires-Dist: langchain-experimental (>=0.0.58,<0.3) ; python_full_version >= "3.8.1" and python_full_version != "3.9.7" and python_version < "4.0"
Requires-Dist: langchainhub (>=0.1.14,<0.3) ; python_full_version >= "3.8.1" and python_full_version != "3.9.7" and python_version < "4.0"
Requires-Dist: zhipuai (>=2.1.0.20240521) ; python_full_version >= "3.8.1" and python_full_version != "3.9.7" and python_version < "3.12"
